{
  "fetchedAt": "2026-04-27T12:07:59.315Z",
  "source": "FantasyCalc",
  "format": "dynasty-superflex-12team-fullppr",
  "playerCount": 442,
  "values": {
    "Josh Allen": {
      "value": 10390,
      "overallRank": 1,
      "positionRank": 1,
      "position": "QB",
      "team": "BUF",
      "trend30Day": -317,
      "sleeperId": "4984"
    },
    "Bijan Robinson": {
      "value": 9890,
      "overallRank": 2,
      "positionRank": 1,
      "position": "RB",
      "team": "ATL",
      "trend30Day": 53,
      "sleeperId": "9509"
    },
    "Ja'Marr Chase": {
      "value": 9792,
      "overallRank": 3,
      "positionRank": 1,
      "position": "WR",
      "team": "CIN",
      "trend30Day": 235,
      "sleeperId": "7564"
    },
    "Jahmyr Gibbs": {
      "value": 9642,
      "overallRank": 4,
      "positionRank": 2,
      "position": "RB",
      "team": "DET",
      "trend30Day": 241,
      "sleeperId": "9221"
    },
    "Jaxon Smith-Njigba": {
      "value": 9415,
      "overallRank": 5,
      "positionRank": 2,
      "position": "WR",
      "team": "SEA",
      "trend30Day": 106,
      "sleeperId": "9488"
    },
    "Drake Maye": {
      "value": 9152,
      "overallRank": 6,
      "positionRank": 2,
      "position": "QB",
      "team": "NE",
      "trend30Day": 334,
      "sleeperId": "11564"
    },
    "Puka Nacua": {
      "value": 8456,
      "overallRank": 7,
      "positionRank": 3,
      "position": "WR",
      "team": "LAR",
      "trend30Day": -379,
      "sleeperId": "9493"
    },
    "Brock Bowers": {
      "value": 7574,
      "overallRank": 8,
      "positionRank": 1,
      "position": "TE",
      "team": "LV",
      "trend30Day": 458,
      "sleeperId": "11604"
    },
    "Jayden Daniels": {
      "value": 7428,
      "overallRank": 9,
      "positionRank": 3,
      "position": "QB",
      "team": "WAS",
      "trend30Day": -108,
      "sleeperId": "11566"
    },
    "Malik Nabers": {
      "value": 7396,
      "overallRank": 10,
      "positionRank": 4,
      "position": "WR",
      "team": "NYG",
      "trend30Day": -1,
      "sleeperId": "11632"
    },
    "Lamar Jackson": {
      "value": 7347,
      "overallRank": 11,
      "positionRank": 4,
      "position": "QB",
      "team": "BAL",
      "trend30Day": -247,
      "sleeperId": "4881"
    },
    "Justin Jefferson": {
      "value": 7341,
      "overallRank": 12,
      "positionRank": 5,
      "position": "WR",
      "team": "MIN",
      "trend30Day": -15,
      "sleeperId": "6794"
    },
    "2026 Pick 1.01": {
      "value": 7257,
      "overallRank": 13,
      "positionRank": 1,
      "position": "PICK",
      "team": null,
      "trend30Day": 160,
      "sleeperId": "DP_0_0"
    },
    "Trey McBride": {
      "value": 7207,
      "overallRank": 13,
      "positionRank": 2,
      "position": "TE",
      "team": "ARI",
      "trend30Day": 29,
      "sleeperId": "8130"
    },
    "Caleb Williams": {
      "value": 7179,
      "overallRank": 14,
      "positionRank": 5,
      "position": "QB",
      "team": "CHI",
      "trend30Day": 233,
      "sleeperId": "11560"
    },
    "Amon-Ra St. Brown": {
      "value": 7071,
      "overallRank": 15,
      "positionRank": 6,
      "position": "WR",
      "team": "DET",
      "trend30Day": -472,
      "sleeperId": "7547"
    },
    "Ashton Jeanty": {
      "value": 6947,
      "overallRank": 16,
      "positionRank": 3,
      "position": "RB",
      "team": "LV",
      "trend30Day": 213,
      "sleeperId": "12527"
    },
    "Jeremiyah Love": {
      "value": 6903,
      "overallRank": 17,
      "positionRank": 4,
      "position": "RB",
      "team": null,
      "trend30Day": -102,
      "sleeperId": "13287"
    },
    "CeeDee Lamb": {
      "value": 6752,
      "overallRank": 18,
      "positionRank": 7,
      "position": "WR",
      "team": "DAL",
      "trend30Day": -73,
      "sleeperId": "6786"
    },
    "Joe Burrow": {
      "value": 6750,
      "overallRank": 19,
      "positionRank": 6,
      "position": "QB",
      "team": "CIN",
      "trend30Day": 97,
      "sleeperId": "6770"
    },
    "De'Von Achane": {
      "value": 6106,
      "overallRank": 20,
      "positionRank": 5,
      "position": "RB",
      "team": "MIA",
      "trend30Day": 70,
      "sleeperId": "9226"
    },
    "Justin Herbert": {
      "value": 5786,
      "overallRank": 21,
      "positionRank": 7,
      "position": "QB",
      "team": "LAC",
      "trend30Day": -203,
      "sleeperId": "6797"
    },
    "Drake London": {
      "value": 5779,
      "overallRank": 22,
      "positionRank": 8,
      "position": "WR",
      "team": "ATL",
      "trend30Day": -6,
      "sleeperId": "8112"
    },
    "Jaxson Dart": {
      "value": 5708,
      "overallRank": 23,
      "positionRank": 8,
      "position": "QB",
      "team": "NYG",
      "trend30Day": 111,
      "sleeperId": "12508"
    },
    "Omarion Hampton": {
      "value": 5625,
      "overallRank": 24,
      "positionRank": 6,
      "position": "RB",
      "team": "LAC",
      "trend30Day": -320,
      "sleeperId": "12507"
    },
    "Patrick Mahomes": {
      "value": 5614,
      "overallRank": 25,
      "positionRank": 9,
      "position": "QB",
      "team": "KC",
      "trend30Day": -203,
      "sleeperId": "4046"
    },
    "Jalen Hurts": {
      "value": 5465,
      "overallRank": 26,
      "positionRank": 10,
      "position": "QB",
      "team": "PHI",
      "trend30Day": -198,
      "sleeperId": "6904"
    },
    "Tetairoa McMillan": {
      "value": 5128,
      "overallRank": 27,
      "positionRank": 9,
      "position": "WR",
      "team": "CAR",
      "trend30Day": 34,
      "sleeperId": "12526"
    },
    "Bo Nix": {
      "value": 5072,
      "overallRank": 28,
      "positionRank": 11,
      "position": "QB",
      "team": "DEN",
      "trend30Day": 2,
      "sleeperId": "11563"
    },
    "Jonathan Taylor": {
      "value": 5037,
      "overallRank": 29,
      "positionRank": 7,
      "position": "RB",
      "team": "IND",
      "trend30Day": -34,
      "sleeperId": "6813"
    },
    "Colston Loveland": {
      "value": 4878,
      "overallRank": 30,
      "positionRank": 3,
      "position": "TE",
      "team": "CHI",
      "trend30Day": -128,
      "sleeperId": "12517"
    },
    "James Cook": {
      "value": 4846,
      "overallRank": 31,
      "positionRank": 8,
      "position": "RB",
      "team": "BUF",
      "trend30Day": -30,
      "sleeperId": "8138"
    },
    "Trevor Lawrence": {
      "value": 4753,
      "overallRank": 32,
      "positionRank": 12,
      "position": "QB",
      "team": "JAX",
      "trend30Day": -187,
      "sleeperId": "7523"
    },
    "2026 Pick 1.02": {
      "value": 4708,
      "overallRank": 33,
      "positionRank": 2,
      "position": "PICK",
      "team": null,
      "trend30Day": -152,
      "sleeperId": "DP_0_1"
    },
    "Emeka Egbuka": {
      "value": 4531,
      "overallRank": 33,
      "positionRank": 10,
      "position": "WR",
      "team": "TB",
      "trend30Day": -19,
      "sleeperId": "12514"
    },
    "Fernando Mendoza": {
      "value": 4460,
      "overallRank": 34,
      "positionRank": 13,
      "position": "QB",
      "team": null,
      "trend30Day": 501,
      "sleeperId": "13269"
    },
    "George Pickens": {
      "value": 4442,
      "overallRank": 35,
      "positionRank": 11,
      "position": "WR",
      "team": "DAL",
      "trend30Day": -364,
      "sleeperId": "8137"
    },
    "Carnell Tate": {
      "value": 4419,
      "overallRank": 36,
      "positionRank": 12,
      "position": "WR",
      "team": null,
      "trend30Day": 45,
      "sleeperId": "13279"
    },
    "Brock Purdy": {
      "value": 4414,
      "overallRank": 37,
      "positionRank": 14,
      "position": "QB",
      "team": "SF",
      "trend30Day": -308,
      "sleeperId": "8183"
    },
    "Tyler Warren": {
      "value": 4314,
      "overallRank": 38,
      "positionRank": 4,
      "position": "TE",
      "team": "IND",
      "trend30Day": -164,
      "sleeperId": "12518"
    },
    "Nico Collins": {
      "value": 4269,
      "overallRank": 39,
      "positionRank": 13,
      "position": "WR",
      "team": "HOU",
      "trend30Day": -208,
      "sleeperId": "7569"
    },
    "2026 Pick 1.03": {
      "value": 4221,
      "overallRank": 40,
      "positionRank": 3,
      "position": "PICK",
      "team": null,
      "trend30Day": 24,
      "sleeperId": "DP_0_2"
    },
    "Garrett Wilson": {
      "value": 4171,
      "overallRank": 40,
      "positionRank": 14,
      "position": "WR",
      "team": "NYJ",
      "trend30Day": 54,
      "sleeperId": "8146"
    },
    "Rashee Rice": {
      "value": 4059,
      "overallRank": 41,
      "positionRank": 15,
      "position": "WR",
      "team": "KC",
      "trend30Day": 519,
      "sleeperId": "10229"
    },
    "Chris Olave": {
      "value": 4050,
      "overallRank": 42,
      "positionRank": 16,
      "position": "WR",
      "team": "NO",
      "trend30Day": -117,
      "sleeperId": "8144"
    },
    "Jordan Love": {
      "value": 4035,
      "overallRank": 43,
      "positionRank": 15,
      "position": "QB",
      "team": "GB",
      "trend30Day": -18,
      "sleeperId": "6804"
    },
    "Kenneth Walker": {
      "value": 4021,
      "overallRank": 44,
      "positionRank": 9,
      "position": "RB",
      "team": "KC",
      "trend30Day": -315,
      "sleeperId": "8151"
    },
    "Christian McCaffrey": {
      "value": 3945,
      "overallRank": 45,
      "positionRank": 10,
      "position": "RB",
      "team": "SF",
      "trend30Day": -127,
      "sleeperId": "4034"
    },
    "2026 Pick 1.04": {
      "value": 3923,
      "overallRank": 46,
      "positionRank": 4,
      "position": "PICK",
      "team": null,
      "trend30Day": 82,
      "sleeperId": "DP_0_3"
    },
    "TreVeyon Henderson": {
      "value": 3909,
      "overallRank": 46,
      "positionRank": 11,
      "position": "RB",
      "team": "NE",
      "trend30Day": 32,
      "sleeperId": "12529"
    },
    "Breece Hall": {
      "value": 3839,
      "overallRank": 47,
      "positionRank": 12,
      "position": "RB",
      "team": "NYJ",
      "trend30Day": -109,
      "sleeperId": "8155"
    },
    "Quinshon Judkins": {
      "value": 3797,
      "overallRank": 48,
      "positionRank": 13,
      "position": "RB",
      "team": "CLE",
      "trend30Day": 189,
      "sleeperId": "12512"
    },
    "Jordyn Tyson": {
      "value": 3761,
      "overallRank": 49,
      "positionRank": 17,
      "position": "WR",
      "team": null,
      "trend30Day": 87,
      "sleeperId": "13281"
    },
    "Makai Lemon": {
      "value": 3734,
      "overallRank": 50,
      "positionRank": 18,
      "position": "WR",
      "team": null,
      "trend30Day": -771,
      "sleeperId": "13294"
    },
    "Ladd McConkey": {
      "value": 3697,
      "overallRank": 51,
      "positionRank": 19,
      "position": "WR",
      "team": "LAC",
      "trend30Day": -398,
      "sleeperId": "11635"
    },
    "Cam Ward": {
      "value": 3696,
      "overallRank": 52,
      "positionRank": 16,
      "position": "QB",
      "team": "TEN",
      "trend30Day": 14,
      "sleeperId": "12522"
    },
    "2026 Pick 1.05": {
      "value": 3653,
      "overallRank": 53,
      "positionRank": 5,
      "position": "PICK",
      "team": null,
      "trend30Day": 154,
      "sleeperId": "DP_0_4"
    },
    "Saquon Barkley": {
      "value": 3606,
      "overallRank": 53,
      "positionRank": 14,
      "position": "RB",
      "team": "PHI",
      "trend30Day": -180,
      "sleeperId": "4866"
    },
    "Brian Thomas": {
      "value": 3582,
      "overallRank": 54,
      "positionRank": 20,
      "position": "WR",
      "team": "JAX",
      "trend30Day": 39,
      "sleeperId": "11631"
    },
    "A.J. Brown": {
      "value": 3579,
      "overallRank": 55,
      "positionRank": 21,
      "position": "WR",
      "team": "PHI",
      "trend30Day": 130,
      "sleeperId": "5859"
    },
    "Dak Prescott": {
      "value": 3576,
      "overallRank": 56,
      "positionRank": 17,
      "position": "QB",
      "team": "DAL",
      "trend30Day": -489,
      "sleeperId": "3294"
    },
    "Marvin Harrison Jr": {
      "value": 3537,
      "overallRank": 57,
      "positionRank": 22,
      "position": "WR",
      "team": "ARI",
      "trend30Day": 83,
      "sleeperId": "11628"
    },
    "Chase Brown": {
      "value": 3480,
      "overallRank": 58,
      "positionRank": 15,
      "position": "RB",
      "team": "CIN",
      "trend30Day": -248,
      "sleeperId": "9224"
    },
    "DeVonta Smith": {
      "value": 3479,
      "overallRank": 59,
      "positionRank": 23,
      "position": "WR",
      "team": "PHI",
      "trend30Day": 366,
      "sleeperId": "7525"
    },
    "Bucky Irving": {
      "value": 3469,
      "overallRank": 60,
      "positionRank": 16,
      "position": "RB",
      "team": "TB",
      "trend30Day": -191,
      "sleeperId": "11584"
    },
    "Kyren Williams": {
      "value": 3469,
      "overallRank": 61,
      "positionRank": 17,
      "position": "RB",
      "team": "LAR",
      "trend30Day": 105,
      "sleeperId": "8150"
    },
    "Tucker Kraft": {
      "value": 3460,
      "overallRank": 62,
      "positionRank": 5,
      "position": "TE",
      "team": "GB",
      "trend30Day": 80,
      "sleeperId": "9484"
    },
    "Luther Burden": {
      "value": 3444,
      "overallRank": 63,
      "positionRank": 24,
      "position": "WR",
      "team": "CHI",
      "trend30Day": -166,
      "sleeperId": "12519"
    },
    "Rome Odunze": {
      "value": 3429,
      "overallRank": 64,
      "positionRank": 25,
      "position": "WR",
      "team": "CHI",
      "trend30Day": -325,
      "sleeperId": "11620"
    },
    "Jared Goff": {
      "value": 3395,
      "overallRank": 65,
      "positionRank": 18,
      "position": "QB",
      "team": "DET",
      "trend30Day": -83,
      "sleeperId": "3163"
    },
    "C.J. Stroud": {
      "value": 3375,
      "overallRank": 66,
      "positionRank": 19,
      "position": "QB",
      "team": "HOU",
      "trend30Day": 14,
      "sleeperId": "9758"
    },
    "Baker Mayfield": {
      "value": 3334,
      "overallRank": 67,
      "positionRank": 20,
      "position": "QB",
      "team": "TB",
      "trend30Day": -149,
      "sleeperId": "4892"
    },
    "Harold Fannin": {
      "value": 3280,
      "overallRank": 68,
      "positionRank": 6,
      "position": "TE",
      "team": "CLE",
      "trend30Day": -90,
      "sleeperId": "12506"
    },
    "2026 Pick 1.06": {
      "value": 3197,
      "overallRank": 69,
      "positionRank": 6,
      "position": "PICK",
      "team": null,
      "trend30Day": 113,
      "sleeperId": "DP_0_5"
    },
    "Jaylen Waddle": {
      "value": 3180,
      "overallRank": 69,
      "positionRank": 26,
      "position": "WR",
      "team": "DEN",
      "trend30Day": -21,
      "sleeperId": "7526"
    },
    "Tee Higgins": {
      "value": 3101,
      "overallRank": 70,
      "positionRank": 27,
      "position": "WR",
      "team": "CIN",
      "trend30Day": -232,
      "sleeperId": "6801"
    },
    "2026 1st": {
      "value": 3070,
      "overallRank": 71,
      "positionRank": 7,
      "position": "PICK",
      "team": null,
      "trend30Day": 148,
      "sleeperId": "FP_2026_1"
    },
    "2027 1st": {
      "value": 3056,
      "overallRank": 71,
      "positionRank": 8,
      "position": "PICK",
      "team": null,
      "trend30Day": 9,
      "sleeperId": "FP_2027_1"
    },
    "Tyler Shough": {
      "value": 3028,
      "overallRank": 71,
      "positionRank": 21,
      "position": "QB",
      "team": "NO",
      "trend30Day": -196,
      "sleeperId": "12545"
    },
    "Jadarian Price": {
      "value": 3020,
      "overallRank": 72,
      "positionRank": 18,
      "position": "RB",
      "team": null,
      "trend30Day": 479,
      "sleeperId": "13286"
    },
    "Zay Flowers": {
      "value": 3019,
      "overallRank": 73,
      "positionRank": 28,
      "position": "WR",
      "team": "BAL",
      "trend30Day": -335,
      "sleeperId": "9997"
    },
    "Travis Etienne": {
      "value": 3016,
      "overallRank": 74,
      "positionRank": 19,
      "position": "RB",
      "team": "NO",
      "trend30Day": -105,
      "sleeperId": "7543"
    },
    "Sam Darnold": {
      "value": 3015,
      "overallRank": 75,
      "positionRank": 22,
      "position": "QB",
      "team": "SEA",
      "trend30Day": -100,
      "sleeperId": "4943"
    },
    "Cam Skattebo": {
      "value": 2999,
      "overallRank": 76,
      "positionRank": 20,
      "position": "RB",
      "team": "NYG",
      "trend30Day": 200,
      "sleeperId": "12481"
    },
    "Josh Jacobs": {
      "value": 2972,
      "overallRank": 77,
      "positionRank": 21,
      "position": "RB",
      "team": "GB",
      "trend30Day": -178,
      "sleeperId": "5850"
    },
    "Sam LaPorta": {
      "value": 2958,
      "overallRank": 78,
      "positionRank": 7,
      "position": "TE",
      "team": "DET",
      "trend30Day": -249,
      "sleeperId": "10859"
    },
    "2026 Pick 1.07": {
      "value": 2944,
      "overallRank": 79,
      "positionRank": 9,
      "position": "PICK",
      "team": null,
      "trend30Day": 184,
      "sleeperId": "DP_0_6"
    },
    "Kenyon Sadiq": {
      "value": 2935,
      "overallRank": 79,
      "positionRank": 8,
      "position": "TE",
      "team": null,
      "trend30Day": -341,
      "sleeperId": "13330"
    },
    "Kyler Murray": {
      "value": 2915,
      "overallRank": 80,
      "positionRank": 23,
      "position": "QB",
      "team": "MIN",
      "trend30Day": -120,
      "sleeperId": "5849"
    },
    "Jameson Williams": {
      "value": 2842,
      "overallRank": 81,
      "positionRank": 29,
      "position": "WR",
      "team": "DET",
      "trend30Day": -105,
      "sleeperId": "8148"
    },
    "Javonte Williams": {
      "value": 2835,
      "overallRank": 82,
      "positionRank": 22,
      "position": "RB",
      "team": "DAL",
      "trend30Day": -162,
      "sleeperId": "7588"
    },
    "KC Concepcion": {
      "value": 2830,
      "overallRank": 83,
      "positionRank": 30,
      "position": "WR",
      "team": null,
      "trend30Day": 72,
      "sleeperId": "13298"
    },
    "Bryce Young": {
      "value": 2721,
      "overallRank": 84,
      "positionRank": 24,
      "position": "QB",
      "team": "CAR",
      "trend30Day": -110,
      "sleeperId": "9228"
    },
    "2026 Pick 1.08": {
      "value": 2686,
      "overallRank": 85,
      "positionRank": 10,
      "position": "PICK",
      "team": null,
      "trend30Day": 107,
      "sleeperId": "DP_0_7"
    },
    "Kyle Pitts": {
      "value": 2653,
      "overallRank": 85,
      "positionRank": 9,
      "position": "TE",
      "team": "ATL",
      "trend30Day": -288,
      "sleeperId": "7553"
    },
    "Derrick Henry": {
      "value": 2528,
      "overallRank": 86,
      "positionRank": 23,
      "position": "RB",
      "team": "BAL",
      "trend30Day": -64,
      "sleeperId": "3198"
    },
    "2026 Pick 1.09": {
      "value": 2524,
      "overallRank": 87,
      "positionRank": 11,
      "position": "PICK",
      "team": null,
      "trend30Day": 45,
      "sleeperId": "DP_0_8"
    },
    "Daniel Jones": {
      "value": 2522,
      "overallRank": 87,
      "positionRank": 25,
      "position": "QB",
      "team": "IND",
      "trend30Day": -222,
      "sleeperId": "5870"
    },
    "Omar Cooper": {
      "value": 2490,
      "overallRank": 88,
      "positionRank": 31,
      "position": "WR",
      "team": null,
      "trend30Day": 261,
      "sleeperId": "13276"
    },
    "Malik Willis": {
      "value": 2416,
      "overallRank": 89,
      "positionRank": 26,
      "position": "QB",
      "team": "MIA",
      "trend30Day": -172,
      "sleeperId": "8161"
    },
    "Ty Simpson": {
      "value": 2392,
      "overallRank": 90,
      "positionRank": 27,
      "position": "QB",
      "team": null,
      "trend30Day": 118,
      "sleeperId": "13275"
    },
    "Matthew Stafford": {
      "value": 2385,
      "overallRank": 91,
      "positionRank": 28,
      "position": "QB",
      "team": "LAR",
      "trend30Day": -58,
      "sleeperId": "421"
    },
    "2026 Pick 1.10": {
      "value": 2368,
      "overallRank": 92,
      "positionRank": 12,
      "position": "PICK",
      "team": null,
      "trend30Day": 16,
      "sleeperId": "DP_0_9"
    },
    "DJ Moore": {
      "value": 2315,
      "overallRank": 92,
      "positionRank": 32,
      "position": "WR",
      "team": "BUF",
      "trend30Day": -302,
      "sleeperId": "4983"
    },
    "Alec Pierce": {
      "value": 2274,
      "overallRank": 93,
      "positionRank": 33,
      "position": "WR",
      "team": "IND",
      "trend30Day": -88,
      "sleeperId": "8142"
    },
    "2026 Pick 1.11": {
      "value": 2258,
      "overallRank": 94,
      "positionRank": 13,
      "position": "PICK",
      "team": null,
      "trend30Day": 21,
      "sleeperId": "DP_0_10"
    },
    "Eli Stowers": {
      "value": 2224,
      "overallRank": 94,
      "positionRank": 10,
      "position": "TE",
      "team": null,
      "trend30Day": -119,
      "sleeperId": "13349"
    },
    "Oronde Gadsden": {
      "value": 2204,
      "overallRank": 95,
      "positionRank": 11,
      "position": "TE",
      "team": "LAC",
      "trend30Day": -85,
      "sleeperId": "12493"
    },
    "Denzel Boston": {
      "value": 2194,
      "overallRank": 96,
      "positionRank": 34,
      "position": "WR",
      "team": null,
      "trend30Day": -612,
      "sleeperId": "13346"
    },
    "2026 Pick 1.12": {
      "value": 2182,
      "overallRank": 97,
      "positionRank": 14,
      "position": "PICK",
      "team": null,
      "trend30Day": 34,
      "sleeperId": "DP_0_11"
    },
    "2028 1st": {
      "value": 2159,
      "overallRank": 97,
      "positionRank": 15,
      "position": "PICK",
      "team": null,
      "trend30Day": -34,
      "sleeperId": "FP_2028_1"
    },
    "RJ Harvey": {
      "value": 2129,
      "overallRank": 97,
      "positionRank": 24,
      "position": "RB",
      "team": "DEN",
      "trend30Day": -177,
      "sleeperId": "12489"
    },
    "Christian Watson": {
      "value": 2099,
      "overallRank": 98,
      "positionRank": 35,
      "position": "WR",
      "team": "GB",
      "trend30Day": 195,
      "sleeperId": "8167"
    },
    "Jordan Addison": {
      "value": 2087,
      "overallRank": 99,
      "positionRank": 36,
      "position": "WR",
      "team": "MIN",
      "trend30Day": -275,
      "sleeperId": "9756"
    },
    "Michael Wilson": {
      "value": 2084,
      "overallRank": 100,
      "positionRank": 37,
      "position": "WR",
      "team": "ARI",
      "trend30Day": -84,
      "sleeperId": "10232"
    },
    "Bhayshul Tuten": {
      "value": 2068,
      "overallRank": 101,
      "positionRank": 25,
      "position": "RB",
      "team": "JAX",
      "trend30Day": -183,
      "sleeperId": "12490"
    },
    "Matthew Golden": {
      "value": 2054,
      "overallRank": 102,
      "positionRank": 38,
      "position": "WR",
      "team": "GB",
      "trend30Day": 20,
      "sleeperId": "12501"
    },
    "George Kittle": {
      "value": 2018,
      "overallRank": 103,
      "positionRank": 12,
      "position": "TE",
      "team": "SF",
      "trend30Day": -29,
      "sleeperId": "4217"
    },
    "Terry McLaurin": {
      "value": 2018,
      "overallRank": 104,
      "positionRank": 39,
      "position": "WR",
      "team": "WAS",
      "trend30Day": -83,
      "sleeperId": "5927"
    },
    "Davante Adams": {
      "value": 2017,
      "overallRank": 105,
      "positionRank": 40,
      "position": "WR",
      "team": "LAR",
      "trend30Day": -158,
      "sleeperId": "2133"
    },
    "Mike Evans": {
      "value": 2014,
      "overallRank": 106,
      "positionRank": 41,
      "position": "WR",
      "team": "SF",
      "trend30Day": 2,
      "sleeperId": "2216"
    },
    "2026 Pick 2.01": {
      "value": 1999,
      "overallRank": 107,
      "positionRank": 16,
      "position": "PICK",
      "team": null,
      "trend30Day": 82,
      "sleeperId": "DP_1_0"
    },
    "Wan'Dale Robinson": {
      "value": 1988,
      "overallRank": 107,
      "positionRank": 42,
      "position": "WR",
      "team": "TEN",
      "trend30Day": -177,
      "sleeperId": "8126"
    },
    "Travis Hunter": {
      "value": 1986,
      "overallRank": 108,
      "positionRank": 43,
      "position": "WR",
      "team": "JAX",
      "trend30Day": -231,
      "sleeperId": "12530"
    },
    "Isaiah Likely": {
      "value": 1984,
      "overallRank": 109,
      "positionRank": 13,
      "position": "TE",
      "team": "NYG",
      "trend30Day": -132,
      "sleeperId": "8131"
    },
    "Jake Ferguson": {
      "value": 1970,
      "overallRank": 110,
      "positionRank": 14,
      "position": "TE",
      "team": "DAL",
      "trend30Day": -34,
      "sleeperId": "8110"
    },
    "D'Andre Swift": {
      "value": 1956,
      "overallRank": 111,
      "positionRank": 26,
      "position": "RB",
      "team": "CHI",
      "trend30Day": -133,
      "sleeperId": "6790"
    },
    "Chuba Hubbard": {
      "value": 1944,
      "overallRank": 112,
      "positionRank": 27,
      "position": "RB",
      "team": "CAR",
      "trend30Day": 3,
      "sleeperId": "7594"
    },
    "2026 Pick 2.02": {
      "value": 1934,
      "overallRank": 113,
      "positionRank": 17,
      "position": "PICK",
      "team": null,
      "trend30Day": 93,
      "sleeperId": "DP_1_1"
    },
    "David Montgomery": {
      "value": 1933,
      "overallRank": 113,
      "positionRank": 28,
      "position": "RB",
      "team": "HOU",
      "trend30Day": -134,
      "sleeperId": "5892"
    },
    "DK Metcalf": {
      "value": 1913,
      "overallRank": 114,
      "positionRank": 44,
      "position": "WR",
      "team": "PIT",
      "trend30Day": -101,
      "sleeperId": "5846"
    },
    "Dalton Kincaid": {
      "value": 1899,
      "overallRank": 115,
      "positionRank": 15,
      "position": "TE",
      "team": "BUF",
      "trend30Day": -21,
      "sleeperId": "10236"
    },
    "Michael Pittman": {
      "value": 1869,
      "overallRank": 116,
      "positionRank": 45,
      "position": "WR",
      "team": "PIT",
      "trend30Day": -133,
      "sleeperId": "6819"
    },
    "2026 Pick 2.03": {
      "value": 1854,
      "overallRank": 117,
      "positionRank": 18,
      "position": "PICK",
      "team": null,
      "trend30Day": 114,
      "sleeperId": "DP_1_2"
    },
    "Parker Washington": {
      "value": 1841,
      "overallRank": 117,
      "positionRank": 46,
      "position": "WR",
      "team": "JAX",
      "trend30Day": -86,
      "sleeperId": "9487"
    },
    "Michael Penix": {
      "value": 1833,
      "overallRank": 118,
      "positionRank": 29,
      "position": "QB",
      "team": "ATL",
      "trend30Day": -20,
      "sleeperId": "11559"
    },
    "Kyle Monangai": {
      "value": 1795,
      "overallRank": 119,
      "positionRank": 29,
      "position": "RB",
      "team": "CHI",
      "trend30Day": 52,
      "sleeperId": "12534"
    },
    "Jayden Reed": {
      "value": 1794,
      "overallRank": 120,
      "positionRank": 47,
      "position": "WR",
      "team": "GB",
      "trend30Day": 98,
      "sleeperId": "10222"
    },
    "Jayden Higgins": {
      "value": 1793,
      "overallRank": 121,
      "positionRank": 48,
      "position": "WR",
      "team": "HOU",
      "trend30Day": -139,
      "sleeperId": "12484"
    },
    "2026 Pick 2.04": {
      "value": 1786,
      "overallRank": 122,
      "positionRank": 19,
      "position": "PICK",
      "team": null,
      "trend30Day": 97,
      "sleeperId": "DP_1_3"
    },
    "Jonah Coleman": {
      "value": 1784,
      "overallRank": 122,
      "positionRank": 30,
      "position": "RB",
      "team": null,
      "trend30Day": -1045,
      "sleeperId": "13345"
    },
    "Brenton Strange": {
      "value": 1757,
      "overallRank": 123,
      "positionRank": 16,
      "position": "TE",
      "team": "JAX",
      "trend30Day": 41,
      "sleeperId": "9480"
    },
    "Nicholas Singleton": {
      "value": 1751,
      "overallRank": 124,
      "positionRank": 31,
      "position": "RB",
      "team": null,
      "trend30Day": -205,
      "sleeperId": "13288"
    },
    "Chris Bell": {
      "value": 1722,
      "overallRank": 125,
      "positionRank": 49,
      "position": "WR",
      "team": null,
      "trend30Day": -17,
      "sleeperId": "13311"
    },
    "Xavier Worthy": {
      "value": 1718,
      "overallRank": 126,
      "positionRank": 50,
      "position": "WR",
      "team": "KC",
      "trend30Day": -116,
      "sleeperId": "11624"
    },
    "Ricky Pearsall": {
      "value": 1703,
      "overallRank": 127,
      "positionRank": 51,
      "position": "WR",
      "team": "SF",
      "trend30Day": -209,
      "sleeperId": "11638"
    },
    "J.J. McCarthy": {
      "value": 1702,
      "overallRank": 128,
      "positionRank": 30,
      "position": "QB",
      "team": "MIN",
      "trend30Day": -96,
      "sleeperId": "11565"
    },
    "Shedeur Sanders": {
      "value": 1700,
      "overallRank": 129,
      "positionRank": 31,
      "position": "QB",
      "team": "CLE",
      "trend30Day": -101,
      "sleeperId": "12524"
    },
    "Zach Charbonnet": {
      "value": 1696,
      "overallRank": 130,
      "positionRank": 32,
      "position": "RB",
      "team": "SEA",
      "trend30Day": -422,
      "sleeperId": "9753"
    },
    "2026 Pick 2.05": {
      "value": 1682,
      "overallRank": 131,
      "positionRank": 20,
      "position": "PICK",
      "team": null,
      "trend30Day": 59,
      "sleeperId": "DP_1_4"
    },
    "Tua Tagovailoa": {
      "value": 1678,
      "overallRank": 131,
      "positionRank": 32,
      "position": "QB",
      "team": "ATL",
      "trend30Day": -104,
      "sleeperId": "6768"
    },
    "Josh Downs": {
      "value": 1655,
      "overallRank": 132,
      "positionRank": 52,
      "position": "WR",
      "team": "IND",
      "trend30Day": 51,
      "sleeperId": "9500"
    },
    "Jaylen Warren": {
      "value": 1653,
      "overallRank": 133,
      "positionRank": 33,
      "position": "RB",
      "team": "PIT",
      "trend30Day": -89,
      "sleeperId": "8228"
    },
    "Jakobi Meyers": {
      "value": 1643,
      "overallRank": 134,
      "positionRank": 53,
      "position": "WR",
      "team": "JAX",
      "trend30Day": -58,
      "sleeperId": "5947"
    },
    "2026 Pick 2.06": {
      "value": 1636,
      "overallRank": 135,
      "positionRank": 21,
      "position": "PICK",
      "team": null,
      "trend30Day": 71,
      "sleeperId": "DP_1_5"
    },
    "Rico Dowdle": {
      "value": 1633,
      "overallRank": 135,
      "positionRank": 34,
      "position": "RB",
      "team": "PIT",
      "trend30Day": -251,
      "sleeperId": "7021"
    },
    "Romeo Doubs": {
      "value": 1629,
      "overallRank": 136,
      "positionRank": 54,
      "position": "WR",
      "team": "NE",
      "trend30Day": -284,
      "sleeperId": "8121"
    },
    "2026 2nd": {
      "value": 1613,
      "overallRank": 137,
      "positionRank": 22,
      "position": "PICK",
      "team": null,
      "trend30Day": 87,
      "sleeperId": "FP_2026_2"
    },
    "Zachariah Branch": {
      "value": 1603,
      "overallRank": 137,
      "positionRank": 55,
      "position": "WR",
      "team": null,
      "trend30Day": -139,
      "sleeperId": "13320"
    },
    "2026 Pick 2.07": {
      "value": 1590,
      "overallRank": 138,
      "positionRank": 23,
      "position": "PICK",
      "team": null,
      "trend30Day": 103,
      "sleeperId": "DP_1_6"
    },
    "Blake Corum": {
      "value": 1585,
      "overallRank": 138,
      "positionRank": 35,
      "position": "RB",
      "team": "LAR",
      "trend30Day": -106,
      "sleeperId": "11586"
    },
    "Jacoby Brissett": {
      "value": 1577,
      "overallRank": 139,
      "positionRank": 33,
      "position": "QB",
      "team": "ARI",
      "trend30Day": -70,
      "sleeperId": "3257"
    },
    "Quentin Johnston": {
      "value": 1573,
      "overallRank": 140,
      "positionRank": 56,
      "position": "WR",
      "team": "LAC",
      "trend30Day": -194,
      "sleeperId": "9754"
    },
    "Rhamondre Stevenson": {
      "value": 1572,
      "overallRank": 141,
      "positionRank": 36,
      "position": "RB",
      "team": "NE",
      "trend30Day": 44,
      "sleeperId": "7611"
    },
    "Elijah Sarratt": {
      "value": 1565,
      "overallRank": 142,
      "positionRank": 57,
      "position": "WR",
      "team": null,
      "trend30Day": -221,
      "sleeperId": "13268"
    },
    "2026 Pick 2.08": {
      "value": 1564,
      "overallRank": 143,
      "positionRank": 24,
      "position": "PICK",
      "team": null,
      "trend30Day": 103,
      "sleeperId": "DP_1_7"
    },
    "Mike Washington": {
      "value": 1561,
      "overallRank": 143,
      "positionRank": 37,
      "position": "RB",
      "team": null,
      "trend30Day": -359,
      "sleeperId": "13305"
    },
    "Courtland Sutton": {
      "value": 1556,
      "overallRank": 144,
      "positionRank": 58,
      "position": "WR",
      "team": "DEN",
      "trend30Day": -266,
      "sleeperId": "5045"
    },
    "Antonio Williams": {
      "value": 1553,
      "overallRank": 145,
      "positionRank": 59,
      "position": "WR",
      "team": null,
      "trend30Day": 103,
      "sleeperId": "13301"
    },
    "Germie Bernard": {
      "value": 1551,
      "overallRank": 146,
      "positionRank": 60,
      "position": "WR",
      "team": null,
      "trend30Day": -50,
      "sleeperId": "13274"
    },
    "J.K. Dobbins": {
      "value": 1550,
      "overallRank": 147,
      "positionRank": 38,
      "position": "RB",
      "team": "DEN",
      "trend30Day": -59,
      "sleeperId": "6806"
    },
    "T.J. Hockenson": {
      "value": 1544,
      "overallRank": 148,
      "positionRank": 17,
      "position": "TE",
      "team": "MIN",
      "trend30Day": 16,
      "sleeperId": "5844"
    },
    "AJ Barner": {
      "value": 1537,
      "overallRank": 149,
      "positionRank": 18,
      "position": "TE",
      "team": "SEA",
      "trend30Day": -21,
      "sleeperId": "11603"
    },
    "Carson Beck": {
      "value": 1536,
      "overallRank": 150,
      "positionRank": 34,
      "position": "QB",
      "team": null,
      "trend30Day": 112,
      "sleeperId": "13272"
    },
    "2026 Pick 2.09": {
      "value": 1520,
      "overallRank": 151,
      "positionRank": 25,
      "position": "PICK",
      "team": null,
      "trend30Day": 94,
      "sleeperId": "DP_1_8"
    },
    "Jalen McMillan": {
      "value": 1513,
      "overallRank": 151,
      "positionRank": 61,
      "position": "WR",
      "team": "TB",
      "trend30Day": -189,
      "sleeperId": "11618"
    },
    "Jacory Croskey-Merritt": {
      "value": 1501,
      "overallRank": 152,
      "positionRank": 39,
      "position": "RB",
      "team": "WAS",
      "trend30Day": 103,
      "sleeperId": "12533"
    },
    "Tony Pollard": {
      "value": 1497,
      "overallRank": 153,
      "positionRank": 40,
      "position": "RB",
      "team": "TEN",
      "trend30Day": 75,
      "sleeperId": "5967"
    },
    "2027 2nd": {
      "value": 1495,
      "overallRank": 154,
      "positionRank": 26,
      "position": "PICK",
      "team": null,
      "trend30Day": -42,
      "sleeperId": "FP_2027_2"
    },
    "Chris Godwin": {
      "value": 1495,
      "overallRank": 154,
      "positionRank": 62,
      "position": "WR",
      "team": "TB",
      "trend30Day": -202,
      "sleeperId": "4037"
    },
    "2026 Pick 2.10": {
      "value": 1493,
      "overallRank": 155,
      "positionRank": 27,
      "position": "PICK",
      "team": null,
      "trend30Day": 107,
      "sleeperId": "DP_1_9"
    },
    "Kaytron Allen": {
      "value": 1493,
      "overallRank": 155,
      "positionRank": 41,
      "position": "RB",
      "team": null,
      "trend30Day": 449,
      "sleeperId": "13405"
    },
    "Chig Okonkwo": {
      "value": 1487,
      "overallRank": 156,
      "positionRank": 19,
      "position": "TE",
      "team": "WAS",
      "trend30Day": -110,
      "sleeperId": "8210"
    },
    "Dallas Goedert": {
      "value": 1487,
      "overallRank": 157,
      "positionRank": 20,
      "position": "TE",
      "team": "PHI",
      "trend30Day": 54,
      "sleeperId": "5022"
    },
    "2026 Pick 2.11": {
      "value": 1486,
      "overallRank": 158,
      "positionRank": 28,
      "position": "PICK",
      "team": null,
      "trend30Day": 105,
      "sleeperId": "DP_1_10"
    },
    "Brandon Aiyuk": {
      "value": 1482,
      "overallRank": 158,
      "positionRank": 63,
      "position": "WR",
      "team": "SF",
      "trend30Day": -48,
      "sleeperId": "6803"
    },
    "Jonathon Brooks": {
      "value": 1472,
      "overallRank": 159,
      "positionRank": 42,
      "position": "RB",
      "team": "CAR",
      "trend30Day": -26,
      "sleeperId": "11583"
    },
    "2026 Pick 2.12": {
      "value": 1468,
      "overallRank": 160,
      "positionRank": 29,
      "position": "PICK",
      "team": null,
      "trend30Day": 107,
      "sleeperId": "DP_1_11"
    },
    "Malachi Fields": {
      "value": 1458,
      "overallRank": 160,
      "positionRank": 64,
      "position": "WR",
      "team": null,
      "trend30Day": 31,
      "sleeperId": "13285"
    },
    "Travis Kelce": {
      "value": 1458,
      "overallRank": 161,
      "positionRank": 21,
      "position": "TE",
      "team": "KC",
      "trend30Day": -107,
      "sleeperId": "1466"
    },
    "Tyler Allgeier": {
      "value": 1449,
      "overallRank": 162,
      "positionRank": 43,
      "position": "RB",
      "team": "ARI",
      "trend30Day": -414,
      "sleeperId": "8132"
    },
    "Mark Andrews": {
      "value": 1447,
      "overallRank": 163,
      "positionRank": 22,
      "position": "TE",
      "team": "BAL",
      "trend30Day": -74,
      "sleeperId": "5012"
    },
    "Chris Brazzell": {
      "value": 1432,
      "overallRank": 164,
      "positionRank": 65,
      "position": "WR",
      "team": null,
      "trend30Day": -241,
      "sleeperId": "13353"
    },
    "Rachaad White": {
      "value": 1431,
      "overallRank": 165,
      "positionRank": 44,
      "position": "RB",
      "team": "WAS",
      "trend30Day": 20,
      "sleeperId": "8136"
    },
    "Emmett Johnson": {
      "value": 1415,
      "overallRank": 166,
      "positionRank": 45,
      "position": "RB",
      "team": null,
      "trend30Day": -668,
      "sleeperId": "13337"
    },
    "Kenneth Gainwell": {
      "value": 1405,
      "overallRank": 167,
      "positionRank": 46,
      "position": "RB",
      "team": "TB",
      "trend30Day": -105,
      "sleeperId": "7567"
    },
    "Tre' Harris": {
      "value": 1396,
      "overallRank": 168,
      "positionRank": 66,
      "position": "WR",
      "team": "LAC",
      "trend30Day": -104,
      "sleeperId": "12509"
    },
    "Khalil Shakir": {
      "value": 1396,
      "overallRank": 169,
      "positionRank": 67,
      "position": "WR",
      "team": "BUF",
      "trend30Day": -85,
      "sleeperId": "8134"
    },
    "Ja'Kobi Lane": {
      "value": 1387,
      "overallRank": 170,
      "positionRank": 68,
      "position": "WR",
      "team": null,
      "trend30Day": -135,
      "sleeperId": "13293"
    },
    "Jalen Coker": {
      "value": 1372,
      "overallRank": 171,
      "positionRank": 69,
      "position": "WR",
      "team": "CAR",
      "trend30Day": -153,
      "sleeperId": "11646"
    },
    "Gunnar Helm": {
      "value": 1363,
      "overallRank": 172,
      "positionRank": 23,
      "position": "TE",
      "team": "TEN",
      "trend30Day": -82,
      "sleeperId": "12502"
    },
    "2026 Pick 3.01": {
      "value": 1358,
      "overallRank": 173,
      "positionRank": 30,
      "position": "PICK",
      "team": null,
      "trend30Day": 142,
      "sleeperId": "DP_2_0"
    },
    "Jordan Mason": {
      "value": 1355,
      "overallRank": 173,
      "positionRank": 47,
      "position": "RB",
      "team": "MIN",
      "trend30Day": -74,
      "sleeperId": "8408"
    },
    "2026 Pick 3.02": {
      "value": 1353,
      "overallRank": 174,
      "positionRank": 31,
      "position": "PICK",
      "team": null,
      "trend30Day": 169,
      "sleeperId": "DP_2_1"
    },
    "Terrance Ferguson": {
      "value": 1350,
      "overallRank": 174,
      "positionRank": 24,
      "position": "TE",
      "team": "LAR",
      "trend30Day": -63,
      "sleeperId": "12487"
    },
    "Geno Smith": {
      "value": 1345,
      "overallRank": 175,
      "positionRank": 35,
      "position": "QB",
      "team": "NYJ",
      "trend30Day": -111,
      "sleeperId": "1373"
    },
    "2028 2nd": {
      "value": 1327,
      "overallRank": 176,
      "positionRank": 32,
      "position": "PICK",
      "team": null,
      "trend30Day": -1,
      "sleeperId": "FP_2028_2"
    },
    "Skyler Bell": {
      "value": 1326,
      "overallRank": 176,
      "positionRank": 70,
      "position": "WR",
      "team": null,
      "trend30Day": 155,
      "sleeperId": "13402"
    },
    "Rashid Shaheed": {
      "value": 1325,
      "overallRank": 177,
      "positionRank": 71,
      "position": "WR",
      "team": "SEA",
      "trend30Day": -3,
      "sleeperId": "8676"
    },
    "Max Klare": {
      "value": 1324,
      "overallRank": 178,
      "positionRank": 25,
      "position": "TE",
      "team": null,
      "trend30Day": -122,
      "sleeperId": "13278"
    },
    "2026 Pick 3.03": {
      "value": 1318,
      "overallRank": 179,
      "positionRank": 33,
      "position": "PICK",
      "team": null,
      "trend30Day": 155,
      "sleeperId": "DP_2_2"
    },
    "Mason Taylor": {
      "value": 1316,
      "overallRank": 179,
      "positionRank": 26,
      "position": "TE",
      "team": "NYJ",
      "trend30Day": -244,
      "sleeperId": "12498"
    },
    "Woody Marks": {
      "value": 1306,
      "overallRank": 180,
      "positionRank": 48,
      "position": "RB",
      "team": "HOU",
      "trend30Day": -50,
      "sleeperId": "12474"
    },
    "Dylan Sampson": {
      "value": 1297,
      "overallRank": 181,
      "positionRank": 49,
      "position": "RB",
      "team": "CLE",
      "trend30Day": 46,
      "sleeperId": "12469"
    },
    "Jerry Jeudy": {
      "value": 1292,
      "overallRank": 182,
      "positionRank": 72,
      "position": "WR",
      "team": "CLE",
      "trend30Day": -36,
      "sleeperId": "6783"
    },
    "Isiah Pacheco": {
      "value": 1268,
      "overallRank": 183,
      "positionRank": 50,
      "position": "RB",
      "team": "DET",
      "trend30Day": -37,
      "sleeperId": "8205"
    },
    "Justin Fields": {
      "value": 1252,
      "overallRank": 184,
      "positionRank": 36,
      "position": "QB",
      "team": "KC",
      "trend30Day": -165,
      "sleeperId": "7591"
    },
    "Tory Horton": {
      "value": 1251,
      "overallRank": 185,
      "positionRank": 73,
      "position": "WR",
      "team": "SEA",
      "trend30Day": 187,
      "sleeperId": "12497"
    },
    "Kirk Cousins": {
      "value": 1247,
      "overallRank": 186,
      "positionRank": 37,
      "position": "QB",
      "team": null,
      "trend30Day": 723,
      "sleeperId": "1166"
    },
    "Chris Rodriguez": {
      "value": 1246,
      "overallRank": 187,
      "positionRank": 51,
      "position": "RB",
      "team": "JAX",
      "trend30Day": -86,
      "sleeperId": "10219"
    },
    "Isaac TeSlaa": {
      "value": 1244,
      "overallRank": 188,
      "positionRank": 74,
      "position": "WR",
      "team": "DET",
      "trend30Day": -68,
      "sleeperId": "12535"
    },
    "Braelon Allen": {
      "value": 1236,
      "overallRank": 189,
      "positionRank": 52,
      "position": "RB",
      "team": "NYJ",
      "trend30Day": 117,
      "sleeperId": "11576"
    },
    "Tyjae Spears": {
      "value": 1231,
      "overallRank": 190,
      "positionRank": 53,
      "position": "RB",
      "team": "TEN",
      "trend30Day": 138,
      "sleeperId": "9508"
    },
    "Tyrone Tracy": {
      "value": 1226,
      "overallRank": 191,
      "positionRank": 54,
      "position": "RB",
      "team": "NYG",
      "trend30Day": 140,
      "sleeperId": "11655"
    },
    "Brian Robinson": {
      "value": 1205,
      "overallRank": 192,
      "positionRank": 55,
      "position": "RB",
      "team": "ATL",
      "trend30Day": 10,
      "sleeperId": "8154"
    },
    "Kaleb Johnson": {
      "value": 1192,
      "overallRank": 193,
      "positionRank": 56,
      "position": "RB",
      "team": "PIT",
      "trend30Day": -94,
      "sleeperId": "12504"
    },
    "Garrett Nussmeier": {
      "value": 1185,
      "overallRank": 194,
      "positionRank": 38,
      "position": "QB",
      "team": null,
      "trend30Day": 485,
      "sleeperId": "13404"
    },
    "Ted Hurst": {
      "value": 1185,
      "overallRank": 195,
      "positionRank": 75,
      "position": "WR",
      "team": null,
      "trend30Day": -75,
      "sleeperId": "13317"
    },
    "Deshaun Watson": {
      "value": 1176,
      "overallRank": 196,
      "positionRank": 39,
      "position": "QB",
      "team": "CLE",
      "trend30Day": 433,
      "sleeperId": "4017"
    },
    "Kayshon Boutte": {
      "value": 1173,
      "overallRank": 197,
      "positionRank": 76,
      "position": "WR",
      "team": "NE",
      "trend30Day": 124,
      "sleeperId": "9504"
    },
    "Dontayvion Wicks": {
      "value": 1172,
      "overallRank": 198,
      "positionRank": 77,
      "position": "WR",
      "team": "GB",
      "trend30Day": 863,
      "sleeperId": "9486"
    },
    "Alvin Kamara": {
      "value": 1166,
      "overallRank": 199,
      "positionRank": 57,
      "position": "RB",
      "team": "NO",
      "trend30Day": 114,
      "sleeperId": "4035"
    },
    "Trey Benson": {
      "value": 1165,
      "overallRank": 200,
      "positionRank": 58,
      "position": "RB",
      "team": "ARI",
      "trend30Day": -227,
      "sleeperId": "11589"
    },
    "2026 Pick 3.04": {
      "value": 1156,
      "overallRank": 201,
      "positionRank": 34,
      "position": "PICK",
      "team": null,
      "trend30Day": 69,
      "sleeperId": "DP_2_3"
    },
    "Troy Franklin": {
      "value": 1156,
      "overallRank": 201,
      "positionRank": 78,
      "position": "WR",
      "team": "DEN",
      "trend30Day": -230,
      "sleeperId": "11627"
    },
    "Aaron Jones": {
      "value": 1145,
      "overallRank": 202,
      "positionRank": 59,
      "position": "RB",
      "team": "MIN",
      "trend30Day": -20,
      "sleeperId": "4199"
    },
    "Tyreek Hill": {
      "value": 1140,
      "overallRank": 203,
      "positionRank": 79,
      "position": "WR",
      "team": null,
      "trend30Day": -280,
      "sleeperId": "3321"
    },
    "Juwan Johnson": {
      "value": 1140,
      "overallRank": 204,
      "positionRank": 27,
      "position": "TE",
      "team": "NO",
      "trend30Day": 46,
      "sleeperId": "7002"
    },
    "Malik Washington": {
      "value": 1131,
      "overallRank": 205,
      "positionRank": 80,
      "position": "WR",
      "team": "MIA",
      "trend30Day": 49,
      "sleeperId": "11610"
    },
    "Adonai Mitchell": {
      "value": 1128,
      "overallRank": 206,
      "positionRank": 81,
      "position": "WR",
      "team": "NYJ",
      "trend30Day": -76,
      "sleeperId": "11625"
    },
    "2026 Pick 3.05": {
      "value": 1123,
      "overallRank": 207,
      "positionRank": 35,
      "position": "PICK",
      "team": null,
      "trend30Day": 68,
      "sleeperId": "DP_2_4"
    },
    "Mac Jones": {
      "value": 1111,
      "overallRank": 207,
      "positionRank": 40,
      "position": "QB",
      "team": "SF",
      "trend30Day": -236,
      "sleeperId": "7527"
    },
    "Jack Bech": {
      "value": 1107,
      "overallRank": 208,
      "positionRank": 82,
      "position": "WR",
      "team": "LV",
      "trend30Day": 102,
      "sleeperId": "12483"
    },
    "Keon Coleman": {
      "value": 1105,
      "overallRank": 209,
      "positionRank": 83,
      "position": "WR",
      "team": "BUF",
      "trend30Day": -226,
      "sleeperId": "11637"
    },
    "Demond Claiborne": {
      "value": 1102,
      "overallRank": 210,
      "positionRank": 60,
      "position": "RB",
      "team": null,
      "trend30Day": -378,
      "sleeperId": "13347"
    },
    "2026 Pick 3.06": {
      "value": 1091,
      "overallRank": 211,
      "positionRank": 36,
      "position": "PICK",
      "team": null,
      "trend30Day": 66,
      "sleeperId": "DP_2_5"
    },
    "Keaton Mitchell": {
      "value": 1086,
      "overallRank": 211,
      "positionRank": 61,
      "position": "RB",
      "team": "LAC",
      "trend30Day": -128,
      "sleeperId": "9511"
    },
    "2026 3rd": {
      "value": 1076,
      "overallRank": 212,
      "positionRank": 37,
      "position": "PICK",
      "team": null,
      "trend30Day": 66,
      "sleeperId": "FP_2026_3"
    },
    "Tank Bigsby": {
      "value": 1071,
      "overallRank": 212,
      "positionRank": 62,
      "position": "RB",
      "team": "PHI",
      "trend30Day": -90,
      "sleeperId": "9225"
    },
    "Cade Klubnik": {
      "value": 1067,
      "overallRank": 213,
      "positionRank": 41,
      "position": "QB",
      "team": null,
      "trend30Day": 424,
      "sleeperId": "13303"
    },
    "Emanuel Wilson": {
      "value": 1065,
      "overallRank": 214,
      "positionRank": 63,
      "position": "RB",
      "team": "SEA",
      "trend30Day": -132,
      "sleeperId": "11435"
    },
    "2026 Pick 3.07": {
      "value": 1061,
      "overallRank": 215,
      "positionRank": 38,
      "position": "PICK",
      "team": null,
      "trend30Day": 65,
      "sleeperId": "DP_2_6"
    },
    "Pat Bryant": {
      "value": 1058,
      "overallRank": 215,
      "positionRank": 84,
      "position": "WR",
      "team": "DEN",
      "trend30Day": -252,
      "sleeperId": "12492"
    },
    "Dalton Schultz": {
      "value": 1043,
      "overallRank": 216,
      "positionRank": 28,
      "position": "TE",
      "team": "HOU",
      "trend30Day": 94,
      "sleeperId": "5001"
    },
    "Chimere Dike": {
      "value": 1036,
      "overallRank": 217,
      "positionRank": 85,
      "position": "WR",
      "team": "TEN",
      "trend30Day": -149,
      "sleeperId": "12540"
    },
    "2026 Pick 3.08": {
      "value": 1033,
      "overallRank": 218,
      "positionRank": 39,
      "position": "PICK",
      "team": null,
      "trend30Day": 64,
      "sleeperId": "DP_2_7"
    },
    "Jauan Jennings": {
      "value": 1026,
      "overallRank": 218,
      "positionRank": 86,
      "position": "WR",
      "team": null,
      "trend30Day": -126,
      "sleeperId": "7049"
    },
    "2026 Pick 3.09": {
      "value": 1006,
      "overallRank": 219,
      "positionRank": 40,
      "position": "PICK",
      "team": null,
      "trend30Day": 62,
      "sleeperId": "DP_2_8"
    },
    "2027 3rd": {
      "value": 1000,
      "overallRank": 219,
      "positionRank": 41,
      "position": "PICK",
      "team": null,
      "trend30Day": -40,
      "sleeperId": "FP_2027_3"
    },
    "2026 Pick 3.10": {
      "value": 981,
      "overallRank": 219,
      "positionRank": 42,
      "position": "PICK",
      "team": null,
      "trend30Day": 61,
      "sleeperId": "DP_2_9"
    },
    "Anthony Richardson": {
      "value": 977,
      "overallRank": 219,
      "positionRank": 42,
      "position": "QB",
      "team": "IND",
      "trend30Day": -317,
      "sleeperId": "9229"
    },
    "James Conner": {
      "value": 976,
      "overallRank": 220,
      "positionRank": 64,
      "position": "RB",
      "team": "ARI",
      "trend30Day": -144,
      "sleeperId": "4137"
    },
    "2026 Pick 3.11": {
      "value": 957,
      "overallRank": 221,
      "positionRank": 43,
      "position": "PICK",
      "team": null,
      "trend30Day": 60,
      "sleeperId": "DP_2_10"
    },
    "David Njoku": {
      "value": 954,
      "overallRank": 221,
      "positionRank": 29,
      "position": "TE",
      "team": null,
      "trend30Day": -159,
      "sleeperId": "4033"
    },
    "Drew Allar": {
      "value": 953,
      "overallRank": 222,
      "positionRank": 43,
      "position": "QB",
      "team": null,
      "trend30Day": -42,
      "sleeperId": "13289"
    },
    "Tank Dell": {
      "value": 952,
      "overallRank": 223,
      "positionRank": 87,
      "position": "WR",
      "team": "HOU",
      "trend30Day": -195,
      "sleeperId": "9502"
    },
    "2028 3rd": {
      "value": 943,
      "overallRank": 224,
      "positionRank": 44,
      "position": "PICK",
      "team": null,
      "trend30Day": -9,
      "sleeperId": "FP_2028_3"
    },
    "Jaylin Noel": {
      "value": 943,
      "overallRank": 224,
      "positionRank": 88,
      "position": "WR",
      "team": "HOU",
      "trend30Day": -138,
      "sleeperId": "12536"
    },
    "Jalen Nailor": {
      "value": 936,
      "overallRank": 225,
      "positionRank": 89,
      "position": "WR",
      "team": "LV",
      "trend30Day": -80,
      "sleeperId": "8180"
    },
    "2026 Pick 3.12": {
      "value": 934,
      "overallRank": 226,
      "positionRank": 45,
      "position": "PICK",
      "team": null,
      "trend30Day": 59,
      "sleeperId": "DP_2_11"
    },
    "Elic Ayomanor": {
      "value": 932,
      "overallRank": 226,
      "positionRank": 90,
      "position": "WR",
      "team": "TEN",
      "trend30Day": -66,
      "sleeperId": "12499"
    },
    "2026 Pick 4.01": {
      "value": 912,
      "overallRank": 227,
      "positionRank": 46,
      "position": "PICK",
      "team": null,
      "trend30Day": 58,
      "sleeperId": "DP_3_0"
    },
    "Hunter Henry": {
      "value": 910,
      "overallRank": 227,
      "positionRank": 30,
      "position": "TE",
      "team": "NE",
      "trend30Day": 30,
      "sleeperId": "3214"
    },
    "2026 Pick 4.02": {
      "value": 891,
      "overallRank": 228,
      "positionRank": 47,
      "position": "PICK",
      "team": null,
      "trend30Day": 57,
      "sleeperId": "DP_3_1"
    },
    "Stefon Diggs": {
      "value": 876,
      "overallRank": 228,
      "positionRank": 91,
      "position": "WR",
      "team": null,
      "trend30Day": 17,
      "sleeperId": "2449"
    },
    "2026 Pick 4.03": {
      "value": 871,
      "overallRank": 229,
      "positionRank": 48,
      "position": "PICK",
      "team": null,
      "trend30Day": 56,
      "sleeperId": "DP_3_2"
    },
    "Tre Tucker": {
      "value": 868,
      "overallRank": 229,
      "positionRank": 92,
      "position": "WR",
      "team": "LV",
      "trend30Day": 16,
      "sleeperId": "10213"
    },
    "Jake Tonges": {
      "value": 859,
      "overallRank": 230,
      "positionRank": 31,
      "position": "TE",
      "team": "SF",
      "trend30Day": -197,
      "sleeperId": "8698"
    },
    "2026 Pick 4.04": {
      "value": 852,
      "overallRank": 231,
      "positionRank": 49,
      "position": "PICK",
      "team": null,
      "trend30Day": 55,
      "sleeperId": "DP_3_3"
    },
    "2026 Pick 4.05": {
      "value": 834,
      "overallRank": 231,
      "positionRank": 50,
      "position": "PICK",
      "team": null,
      "trend30Day": 54,
      "sleeperId": "DP_3_4"
    },
    "2026 Pick 4.06": {
      "value": 816,
      "overallRank": 231,
      "positionRank": 51,
      "position": "PICK",
      "team": null,
      "trend30Day": 53,
      "sleeperId": "DP_3_5"
    },
    "Theo Johnson": {
      "value": 814,
      "overallRank": 231,
      "positionRank": 32,
      "position": "TE",
      "team": "NYG",
      "trend30Day": -137,
      "sleeperId": "11597"
    },
    "Will Howard": {
      "value": 812,
      "overallRank": 232,
      "positionRank": 44,
      "position": "QB",
      "team": "PIT",
      "trend30Day": 328,
      "sleeperId": "12511"
    },
    "2026 4th": {
      "value": 808,
      "overallRank": 233,
      "positionRank": 52,
      "position": "PICK",
      "team": null,
      "trend30Day": 53,
      "sleeperId": "FP_2026_4"
    },
    "Ollie Gordon": {
      "value": 806,
      "overallRank": 233,
      "positionRank": 65,
      "position": "RB",
      "team": "MIA",
      "trend30Day": -37,
      "sleeperId": "12495"
    },
    "2027 4th": {
      "value": 805,
      "overallRank": 234,
      "positionRank": 53,
      "position": "PICK",
      "team": null,
      "trend30Day": 30,
      "sleeperId": "FP_2027_4"
    },
    "Michael Trigg": {
      "value": 802,
      "overallRank": 234,
      "positionRank": 33,
      "position": "TE",
      "team": null,
      "trend30Day": 71,
      "sleeperId": "13401"
    },
    "Kyle Williams": {
      "value": 802,
      "overallRank": 235,
      "positionRank": 93,
      "position": "WR",
      "team": "NE",
      "trend30Day": -375,
      "sleeperId": "12547"
    },
    "2026 Pick 4.07": {
      "value": 799,
      "overallRank": 236,
      "positionRank": 54,
      "position": "PICK",
      "team": null,
      "trend30Day": 52,
      "sleeperId": "DP_3_6"
    },
    "Kevin Coleman": {
      "value": 798,
      "overallRank": 236,
      "positionRank": 94,
      "position": "WR",
      "team": null,
      "trend30Day": 216,
      "sleeperId": "13338"
    },
    "Cade Otton": {
      "value": 796,
      "overallRank": 237,
      "positionRank": 34,
      "position": "TE",
      "team": "TB",
      "trend30Day": -240,
      "sleeperId": "8111"
    },
    "2026 Pick 4.08": {
      "value": 783,
      "overallRank": 238,
      "positionRank": 55,
      "position": "PICK",
      "team": null,
      "trend30Day": 51,
      "sleeperId": "DP_3_7"
    },
    "Elijah Arroyo": {
      "value": 779,
      "overallRank": 238,
      "positionRank": 35,
      "position": "TE",
      "team": "SEA",
      "trend30Day": 30,
      "sleeperId": "12521"
    },
    "Jordan James": {
      "value": 772,
      "overallRank": 239,
      "positionRank": 66,
      "position": "RB",
      "team": "SF",
      "trend30Day": 15,
      "sleeperId": "12467"
    },
    "Deebo Samuel": {
      "value": 771,
      "overallRank": 240,
      "positionRank": 95,
      "position": "WR",
      "team": null,
      "trend30Day": -227,
      "sleeperId": "5872"
    },
    "Pat Freiermuth": {
      "value": 769,
      "overallRank": 241,
      "positionRank": 36,
      "position": "TE",
      "team": "PIT",
      "trend30Day": -71,
      "sleeperId": "7600"
    },
    "2026 Pick 4.09": {
      "value": 768,
      "overallRank": 242,
      "positionRank": 56,
      "position": "PICK",
      "team": null,
      "trend30Day": 51,
      "sleeperId": "DP_3_8"
    },
    "Aaron Rodgers": {
      "value": 766,
      "overallRank": 242,
      "positionRank": 45,
      "position": "QB",
      "team": null,
      "trend30Day": 3,
      "sleeperId": "96"
    },
    "2028 4th": {
      "value": 760,
      "overallRank": 243,
      "positionRank": 57,
      "position": "PICK",
      "team": null,
      "trend30Day": -4,
      "sleeperId": "FP_2028_4"
    },
    "Jaydon Blue": {
      "value": 756,
      "overallRank": 243,
      "positionRank": 67,
      "position": "RB",
      "team": "DAL",
      "trend30Day": 39,
      "sleeperId": "12457"
    },
    "2026 Pick 4.10": {
      "value": 753,
      "overallRank": 244,
      "positionRank": 58,
      "position": "PICK",
      "team": null,
      "trend30Day": 50,
      "sleeperId": "DP_3_9"
    },
    "Kimani Vidal": {
      "value": 743,
      "overallRank": 244,
      "positionRank": 68,
      "position": "RB",
      "team": "LAC",
      "trend30Day": 1,
      "sleeperId": "11647"
    },
    "2026 Pick 4.11": {
      "value": 739,
      "overallRank": 245,
      "positionRank": 59,
      "position": "PICK",
      "team": null,
      "trend30Day": 49,
      "sleeperId": "DP_3_10"
    },
    "2026 Pick 4.12": {
      "value": 725,
      "overallRank": 245,
      "positionRank": 60,
      "position": "PICK",
      "team": null,
      "trend30Day": 48,
      "sleeperId": "DP_3_11"
    },
    "Isaiah Bond": {
      "value": 709,
      "overallRank": 245,
      "positionRank": 96,
      "position": "WR",
      "team": "CLE",
      "trend30Day": -71,
      "sleeperId": "12503"
    },
    "Darnell Mooney": {
      "value": 698,
      "overallRank": 246,
      "positionRank": 97,
      "position": "WR",
      "team": "NYG",
      "trend30Day": -120,
      "sleeperId": "7090"
    },
    "Devin Neal": {
      "value": 689,
      "overallRank": 247,
      "positionRank": 69,
      "position": "RB",
      "team": "NO",
      "trend30Day": -19,
      "sleeperId": "12476"
    },
    "Calvin Ridley": {
      "value": 681,
      "overallRank": 248,
      "positionRank": 98,
      "position": "WR",
      "team": "TEN",
      "trend30Day": 16,
      "sleeperId": "4981"
    },
    "Jaylen Wright": {
      "value": 677,
      "overallRank": 249,
      "positionRank": 70,
      "position": "RB",
      "team": "MIA",
      "trend30Day": 106,
      "sleeperId": "11643"
    },
    "Evan Engram": {
      "value": 674,
      "overallRank": 250,
      "positionRank": 37,
      "position": "TE",
      "team": "DEN",
      "trend30Day": 25,
      "sleeperId": "4066"
    },
    "Tez Johnson": {
      "value": 666,
      "overallRank": 251,
      "positionRank": 99,
      "position": "WR",
      "team": "TB",
      "trend30Day": -70,
      "sleeperId": "12485"
    },
    "Michael Mayer": {
      "value": 611,
      "overallRank": 252,
      "positionRank": 38,
      "position": "TE",
      "team": "LV",
      "trend30Day": -115,
      "sleeperId": "9482"
    },
    "Oscar Delp": {
      "value": 610,
      "overallRank": 253,
      "positionRank": 39,
      "position": "TE",
      "team": null,
      "trend30Day": -347,
      "sleeperId": "13319"
    },
    "Dont'e Thornton": {
      "value": 605,
      "overallRank": 254,
      "positionRank": 100,
      "position": "WR",
      "team": "LV",
      "trend30Day": -68,
      "sleeperId": "12541"
    },
    "Deion Burks": {
      "value": 591,
      "overallRank": 255,
      "positionRank": 101,
      "position": "WR",
      "team": null,
      "trend30Day": -599,
      "sleeperId": "13333"
    },
    "Le'Veon Moss": {
      "value": 584,
      "overallRank": 256,
      "positionRank": 71,
      "position": "RB",
      "team": null,
      "trend30Day": -605,
      "sleeperId": "13300"
    },
    "Jack Endries": {
      "value": 570,
      "overallRank": 257,
      "positionRank": 40,
      "position": "TE",
      "team": null,
      "trend30Day": -595,
      "sleeperId": "13282"
    },
    "Jam Miller": {
      "value": 569,
      "overallRank": 258,
      "positionRank": 72,
      "position": "RB",
      "team": null,
      "trend30Day": 31,
      "sleeperId": "13403"
    },
    "Christian Kirk": {
      "value": 566,
      "overallRank": 259,
      "positionRank": 102,
      "position": "WR",
      "team": "SF",
      "trend30Day": 88,
      "sleeperId": "4950"
    },
    "Sean Tucker": {
      "value": 561,
      "overallRank": 260,
      "positionRank": 73,
      "position": "RB",
      "team": "TB",
      "trend30Day": -264,
      "sleeperId": "9506"
    },
    "Jalen Milroe": {
      "value": 537,
      "overallRank": 261,
      "positionRank": 46,
      "position": "QB",
      "team": "SEA",
      "trend30Day": -110,
      "sleeperId": "12510"
    },
    "Xavier Legette": {
      "value": 531,
      "overallRank": 262,
      "positionRank": 103,
      "position": "WR",
      "team": "CAR",
      "trend30Day": -49,
      "sleeperId": "11626"
    },
    "Jalen Tolbert": {
      "value": 530,
      "overallRank": 263,
      "positionRank": 104,
      "position": "WR",
      "team": "MIA",
      "trend30Day": 188,
      "sleeperId": "8117"
    },
    "Justin Joly": {
      "value": 528,
      "overallRank": 264,
      "positionRank": 41,
      "position": "TE",
      "team": null,
      "trend30Day": -80,
      "sleeperId": "13400"
    },
    "LeQuint Allen": {
      "value": 527,
      "overallRank": 265,
      "positionRank": 74,
      "position": "RB",
      "team": "JAX",
      "trend30Day": 56,
      "sleeperId": "12544"
    },
    "Adam Randall": {
      "value": 523,
      "overallRank": 266,
      "positionRank": 75,
      "position": "RB",
      "team": null,
      "trend30Day": -766,
      "sleeperId": "13302"
    },
    "Greg Dulcich": {
      "value": 518,
      "overallRank": 267,
      "positionRank": 42,
      "position": "TE",
      "team": "MIA",
      "trend30Day": 256,
      "sleeperId": "8172"
    },
    "Taylen Green": {
      "value": 504,
      "overallRank": 268,
      "positionRank": 47,
      "position": "QB",
      "team": null,
      "trend30Day": -682,
      "sleeperId": "13306"
    },
    "Brashard Smith": {
      "value": 504,
      "overallRank": 269,
      "positionRank": 76,
      "position": "RB",
      "team": "KC",
      "trend30Day": -195,
      "sleeperId": "12455"
    },
    "DJ Giddens": {
      "value": 497,
      "overallRank": 270,
      "positionRank": 77,
      "position": "RB",
      "team": "IND",
      "trend30Day": -84,
      "sleeperId": "12471"
    },
    "Marvin Mims": {
      "value": 491,
      "overallRank": 271,
      "positionRank": 105,
      "position": "WR",
      "team": "DEN",
      "trend30Day": 29,
      "sleeperId": "9494"
    },
    "Caleb Douglas": {
      "value": 482,
      "overallRank": 272,
      "positionRank": 106,
      "position": "WR",
      "team": null,
      "trend30Day": 482,
      "sleeperId": "13296"
    },
    "J'Mari Taylor": {
      "value": 477,
      "overallRank": 273,
      "positionRank": 78,
      "position": "RB",
      "team": null,
      "trend30Day": -595,
      "sleeperId": "13348"
    },
    "Ray Davis": {
      "value": 475,
      "overallRank": 274,
      "positionRank": 79,
      "position": "RB",
      "team": "BUF",
      "trend30Day": 83,
      "sleeperId": "11575"
    },
    "Riley Leonard": {
      "value": 467,
      "overallRank": 275,
      "positionRank": 48,
      "position": "QB",
      "team": "IND",
      "trend30Day": -40,
      "sleeperId": "12470"
    },
    "Brenen Thompson": {
      "value": 466,
      "overallRank": 276,
      "positionRank": 107,
      "position": "WR",
      "team": null,
      "trend30Day": -785,
      "sleeperId": "13380"
    },
    "Colby Parkinson": {
      "value": 465,
      "overallRank": 277,
      "positionRank": 43,
      "position": "TE",
      "team": "LAR",
      "trend30Day": -63,
      "sleeperId": "6865"
    },
    "Cooper Kupp": {
      "value": 462,
      "overallRank": 278,
      "positionRank": 108,
      "position": "WR",
      "team": "SEA",
      "trend30Day": 36,
      "sleeperId": "4039"
    },
    "Ja'Tavion Sanders": {
      "value": 452,
      "overallRank": 279,
      "positionRank": 44,
      "position": "TE",
      "team": "CAR",
      "trend30Day": 36,
      "sleeperId": "11600"
    },
    "Trevor Etienne": {
      "value": 441,
      "overallRank": 280,
      "positionRank": 80,
      "position": "RB",
      "team": "CAR",
      "trend30Day": 40,
      "sleeperId": "12531"
    },
    "Najee Harris": {
      "value": 417,
      "overallRank": 281,
      "positionRank": 81,
      "position": "RB",
      "team": null,
      "trend30Day": -339,
      "sleeperId": "7528"
    },
    "Joe Mixon": {
      "value": 417,
      "overallRank": 282,
      "positionRank": 82,
      "position": "RB",
      "team": null,
      "trend30Day": -47,
      "sleeperId": "4018"
    },
    "Ben Sinnott": {
      "value": 409,
      "overallRank": 283,
      "positionRank": 45,
      "position": "TE",
      "team": "WAS",
      "trend30Day": -3,
      "sleeperId": "11596"
    },
    "Keenan Allen": {
      "value": 403,
      "overallRank": 284,
      "positionRank": 109,
      "position": "WR",
      "team": null,
      "trend30Day": 117,
      "sleeperId": "1479"
    },
    "Marcus Mariota": {
      "value": 389,
      "overallRank": 285,
      "positionRank": 49,
      "position": "QB",
      "team": "WAS",
      "trend30Day": -2,
      "sleeperId": "2307"
    },
    "MarShawn Lloyd": {
      "value": 382,
      "overallRank": 286,
      "positionRank": 83,
      "position": "RB",
      "team": "GB",
      "trend30Day": 131,
      "sleeperId": "11581"
    },
    "Devaughn Vele": {
      "value": 349,
      "overallRank": 287,
      "positionRank": 110,
      "position": "WR",
      "team": "NO",
      "trend30Day": -48,
      "sleeperId": "11834"
    },
    "Joe Milton": {
      "value": 349,
      "overallRank": 288,
      "positionRank": 50,
      "position": "QB",
      "team": "DAL",
      "trend30Day": 31,
      "sleeperId": "11557"
    },
    "Marquise Brown": {
      "value": 344,
      "overallRank": 289,
      "positionRank": 111,
      "position": "WR",
      "team": "PHI",
      "trend30Day": -102,
      "sleeperId": "5848"
    },
    "Quinn Ewers": {
      "value": 341,
      "overallRank": 290,
      "positionRank": 51,
      "position": "QB",
      "team": "MIA",
      "trend30Day": -118,
      "sleeperId": "12500"
    },
    "Cedric Tillman": {
      "value": 341,
      "overallRank": 291,
      "positionRank": 112,
      "position": "WR",
      "team": "CLE",
      "trend30Day": -34,
      "sleeperId": "10444"
    },
    "Cole Payton": {
      "value": 329,
      "overallRank": 292,
      "positionRank": 52,
      "position": "QB",
      "team": null,
      "trend30Day": -298,
      "sleeperId": "13335"
    },
    "Cole Kmet": {
      "value": 320,
      "overallRank": 293,
      "positionRank": 46,
      "position": "TE",
      "team": "CHI",
      "trend30Day": -95,
      "sleeperId": "6826"
    },
    "Joe Flacco": {
      "value": 311,
      "overallRank": 294,
      "positionRank": 53,
      "position": "QB",
      "team": null,
      "trend30Day": -263,
      "sleeperId": "19"
    },
    "Rashod Bateman": {
      "value": 306,
      "overallRank": 295,
      "positionRank": 113,
      "position": "WR",
      "team": "BAL",
      "trend30Day": -18,
      "sleeperId": "7571"
    },
    "Tahj Brooks": {
      "value": 296,
      "overallRank": 296,
      "positionRank": 84,
      "position": "RB",
      "team": "CIN",
      "trend30Day": 105,
      "sleeperId": "12543"
    },
    "Jaylin Lane": {
      "value": 291,
      "overallRank": 297,
      "positionRank": 114,
      "position": "WR",
      "team": "WAS",
      "trend30Day": -44,
      "sleeperId": "12641"
    },
    "Mike Gesicki": {
      "value": 272,
      "overallRank": 298,
      "positionRank": 47,
      "position": "TE",
      "team": "CIN",
      "trend30Day": 118,
      "sleeperId": "4993"
    },
    "Sam Roush": {
      "value": 269,
      "overallRank": 299,
      "positionRank": 48,
      "position": "TE",
      "team": null,
      "trend30Day": -372,
      "sleeperId": "13322"
    },
    "Isaiah Davis": {
      "value": 265,
      "overallRank": 300,
      "positionRank": 85,
      "position": "RB",
      "team": "NYJ",
      "trend30Day": -30,
      "sleeperId": "11571"
    },
    "Darnell Washington": {
      "value": 257,
      "overallRank": 301,
      "positionRank": 49,
      "position": "TE",
      "team": "PIT",
      "trend30Day": 67,
      "sleeperId": "9479"
    },
    "Jalen Royals": {
      "value": 244,
      "overallRank": 302,
      "positionRank": 115,
      "position": "WR",
      "team": "KC",
      "trend30Day": -14,
      "sleeperId": "12505"
    },
    "Marlin Klein": {
      "value": 239,
      "overallRank": 303,
      "positionRank": 50,
      "position": "TE",
      "team": null,
      "trend30Day": -628,
      "sleeperId": "13307"
    },
    "Tyquan Thornton": {
      "value": 231,
      "overallRank": 304,
      "positionRank": 116,
      "position": "WR",
      "team": "KC",
      "trend30Day": 85,
      "sleeperId": "8188"
    },
    "Kendre Miller": {
      "value": 231,
      "overallRank": 305,
      "positionRank": 86,
      "position": "RB",
      "team": "NO",
      "trend30Day": -45,
      "sleeperId": "9757"
    },
    "Jarquez Hunter": {
      "value": 229,
      "overallRank": 306,
      "positionRank": 87,
      "position": "RB",
      "team": "LAR",
      "trend30Day": -53,
      "sleeperId": "11569"
    },
    "Jahan Dotson": {
      "value": 228,
      "overallRank": 307,
      "positionRank": 117,
      "position": "WR",
      "team": "ATL",
      "trend30Day": -52,
      "sleeperId": "8119"
    },
    "Luke McCaffrey": {
      "value": 227,
      "overallRank": 308,
      "positionRank": 118,
      "position": "WR",
      "team": "WAS",
      "trend30Day": 56,
      "sleeperId": "11650"
    },
    "Jameis Winston": {
      "value": 218,
      "overallRank": 309,
      "positionRank": 54,
      "position": "QB",
      "team": "NYG",
      "trend30Day": -37,
      "sleeperId": "2306"
    },
    "Darius Slayton": {
      "value": 216,
      "overallRank": 310,
      "positionRank": 119,
      "position": "WR",
      "team": "NYG",
      "trend30Day": 52,
      "sleeperId": "6149"
    },
    "Davis Mills": {
      "value": 214,
      "overallRank": 311,
      "positionRank": 55,
      "position": "QB",
      "team": "HOU",
      "trend30Day": 68,
      "sleeperId": "7585"
    },
    "Ryan Flournoy": {
      "value": 211,
      "overallRank": 312,
      "positionRank": 120,
      "position": "WR",
      "team": "DAL",
      "trend30Day": -153,
      "sleeperId": "11783"
    },
    "Savion Williams": {
      "value": 206,
      "overallRank": 313,
      "positionRank": 121,
      "position": "WR",
      "team": "GB",
      "trend30Day": 131,
      "sleeperId": "12482"
    },
    "Andrei Iosivas": {
      "value": 206,
      "overallRank": 314,
      "positionRank": 122,
      "position": "WR",
      "team": "CIN",
      "trend30Day": 81,
      "sleeperId": "10226"
    },
    "Calvin Austin": {
      "value": 205,
      "overallRank": 315,
      "positionRank": 123,
      "position": "WR",
      "team": "NYG",
      "trend30Day": -47,
      "sleeperId": "8125"
    },
    "Tyson Bagent": {
      "value": 199,
      "overallRank": 316,
      "positionRank": 56,
      "position": "QB",
      "team": "CHI",
      "trend30Day": 67,
      "sleeperId": "11256"
    },
    "CJ Daniels": {
      "value": 198,
      "overallRank": 317,
      "positionRank": 124,
      "position": "WR",
      "team": null,
      "trend30Day": -902,
      "sleeperId": "13270"
    },
    "Eric McAlister": {
      "value": 198,
      "overallRank": 318,
      "positionRank": 125,
      "position": "WR",
      "team": null,
      "trend30Day": -960,
      "sleeperId": "13354"
    },
    "Will Levis": {
      "value": 197,
      "overallRank": 319,
      "positionRank": 57,
      "position": "QB",
      "team": "TEN",
      "trend30Day": 38,
      "sleeperId": "9999"
    },
    "Luke Musgrave": {
      "value": 182,
      "overallRank": 320,
      "positionRank": 51,
      "position": "TE",
      "team": "GB",
      "trend30Day": 35,
      "sleeperId": "9481"
    },
    "Justice Hill": {
      "value": 180,
      "overallRank": 321,
      "positionRank": 88,
      "position": "RB",
      "team": "BAL",
      "trend30Day": 39,
      "sleeperId": "5995"
    },
    "Isaac Guerendo": {
      "value": 179,
      "overallRank": 322,
      "positionRank": 89,
      "position": "RB",
      "team": "SF",
      "trend30Day": -4,
      "sleeperId": "11651"
    },
    "Dawson Knox": {
      "value": 175,
      "overallRank": 323,
      "positionRank": 52,
      "position": "TE",
      "team": "BUF",
      "trend30Day": 44,
      "sleeperId": "5906"
    },
    "Jeff Caldwell": {
      "value": 172,
      "overallRank": 324,
      "positionRank": 126,
      "position": "WR",
      "team": null,
      "trend30Day": -285,
      "sleeperId": "13392"
    },
    "Malik Benson": {
      "value": 172,
      "overallRank": 325,
      "positionRank": 127,
      "position": "WR",
      "team": null,
      "trend30Day": -160,
      "sleeperId": "13329"
    },
    "DeMario Douglas": {
      "value": 170,
      "overallRank": 326,
      "positionRank": 128,
      "position": "WR",
      "team": "NE",
      "trend30Day": -85,
      "sleeperId": "9501"
    },
    "Mack Hollins": {
      "value": 166,
      "overallRank": 327,
      "positionRank": 129,
      "position": "WR",
      "team": "NE",
      "trend30Day": 51,
      "sleeperId": "4177"
    },
    "Spencer Rattler": {
      "value": 160,
      "overallRank": 328,
      "positionRank": 58,
      "position": "QB",
      "team": "NO",
      "trend30Day": -37,
      "sleeperId": "11562"
    },
    "Ja'Lynn Polk": {
      "value": 160,
      "overallRank": 329,
      "positionRank": 130,
      "position": "WR",
      "team": "NO",
      "trend30Day": -55,
      "sleeperId": "11619"
    },
    "John Metchie": {
      "value": 157,
      "overallRank": 330,
      "positionRank": 131,
      "position": "WR",
      "team": "CAR",
      "trend30Day": -103,
      "sleeperId": "8147"
    },
    "Audric Estime": {
      "value": 157,
      "overallRank": 331,
      "positionRank": 90,
      "position": "RB",
      "team": "NO",
      "trend30Day": -28,
      "sleeperId": "11579"
    },
    "Kareem Hunt": {
      "value": 157,
      "overallRank": 332,
      "positionRank": 91,
      "position": "RB",
      "team": null,
      "trend30Day": 17,
      "sleeperId": "4098"
    },
    "Trey Lance": {
      "value": 151,
      "overallRank": 333,
      "positionRank": 59,
      "position": "QB",
      "team": "LAC",
      "trend30Day": 0,
      "sleeperId": "7610"
    },
    "Noah Gray": {
      "value": 135,
      "overallRank": 334,
      "positionRank": 53,
      "position": "TE",
      "team": "KC",
      "trend30Day": -45,
      "sleeperId": "7828"
    },
    "Kenny Pickett": {
      "value": 134,
      "overallRank": 335,
      "positionRank": 60,
      "position": "QB",
      "team": "CAR",
      "trend30Day": 27,
      "sleeperId": "8160"
    },
    "Michael Carter": {
      "value": 133,
      "overallRank": 336,
      "positionRank": 92,
      "position": "RB",
      "team": null,
      "trend30Day": 51,
      "sleeperId": "7607"
    },
    "Dillon Gabriel": {
      "value": 132,
      "overallRank": 337,
      "positionRank": 61,
      "position": "QB",
      "team": "CLE",
      "trend30Day": -1,
      "sleeperId": "12486"
    },
    "Zonovan Knight": {
      "value": 124,
      "overallRank": 338,
      "positionRank": 93,
      "position": "RB",
      "team": "ARI",
      "trend30Day": 15,
      "sleeperId": "8122"
    },
    "Tanner McKee": {
      "value": 123,
      "overallRank": 339,
      "positionRank": 62,
      "position": "QB",
      "team": "PHI",
      "trend30Day": 30,
      "sleeperId": "9230"
    },
    "Xavier Hutchinson": {
      "value": 122,
      "overallRank": 340,
      "positionRank": 132,
      "position": "WR",
      "team": "HOU",
      "trend30Day": 60,
      "sleeperId": "10218"
    },
    "KeAndre Lambert-Smith": {
      "value": 120,
      "overallRank": 341,
      "positionRank": 133,
      "position": "WR",
      "team": "LAC",
      "trend30Day": 46,
      "sleeperId": "12670"
    },
    "Jerome Ford": {
      "value": 120,
      "overallRank": 342,
      "positionRank": 94,
      "position": "RB",
      "team": "WAS",
      "trend30Day": -70,
      "sleeperId": "8143"
    },
    "Mason Rudolph": {
      "value": 116,
      "overallRank": 343,
      "positionRank": 63,
      "position": "QB",
      "team": "PIT",
      "trend30Day": 116,
      "sleeperId": "4972"
    },
    "Noah Fant": {
      "value": 109,
      "overallRank": 344,
      "positionRank": 54,
      "position": "TE",
      "team": "NO",
      "trend30Day": -24,
      "sleeperId": "5857"
    },
    "Jahdae Walker": {
      "value": 107,
      "overallRank": 345,
      "positionRank": 134,
      "position": "WR",
      "team": "CHI",
      "trend30Day": 16,
      "sleeperId": "13079"
    },
    "Darren Waller": {
      "value": 105,
      "overallRank": 346,
      "positionRank": 55,
      "position": "TE",
      "team": null,
      "trend30Day": 11,
      "sleeperId": "2505"
    },
    "Nick Chubb": {
      "value": 104,
      "overallRank": 347,
      "positionRank": 95,
      "position": "RB",
      "team": null,
      "trend30Day": 104,
      "sleeperId": "4988"
    },
    "Gardner Minshew": {
      "value": 101,
      "overallRank": 348,
      "positionRank": 64,
      "position": "QB",
      "team": "ARI",
      "trend30Day": -208,
      "sleeperId": "6011"
    },
    "Emari Demercado": {
      "value": 100,
      "overallRank": 349,
      "positionRank": 96,
      "position": "RB",
      "team": "KC",
      "trend30Day": -59,
      "sleeperId": "11199"
    },
    "Roman Wilson": {
      "value": 98,
      "overallRank": 350,
      "positionRank": 135,
      "position": "WR",
      "team": "PIT",
      "trend30Day": -8,
      "sleeperId": "11630"
    },
    "George Holani": {
      "value": 96,
      "overallRank": 351,
      "positionRank": 97,
      "position": "RB",
      "team": "SEA",
      "trend30Day": -9,
      "sleeperId": "12048"
    },
    "Matthew Hibner": {
      "value": 92,
      "overallRank": 352,
      "positionRank": 56,
      "position": "TE",
      "team": null,
      "trend30Day": 92,
      "sleeperId": "13324"
    },
    "Carson Wentz": {
      "value": 91,
      "overallRank": 353,
      "positionRank": 65,
      "position": "QB",
      "team": "MIN",
      "trend30Day": -52,
      "sleeperId": "3161"
    },
    "Kenny McIntosh": {
      "value": 89,
      "overallRank": 354,
      "positionRank": 98,
      "position": "RB",
      "team": "SEA",
      "trend30Day": -50,
      "sleeperId": "10216"
    },
    "Treylon Burks": {
      "value": 86,
      "overallRank": 355,
      "positionRank": 136,
      "position": "WR",
      "team": "WAS",
      "trend30Day": -8,
      "sleeperId": "8135"
    },
    "Austin Ekeler": {
      "value": 76,
      "overallRank": 356,
      "positionRank": 99,
      "position": "RB",
      "team": null,
      "trend30Day": 76,
      "sleeperId": "4663"
    },
    "Will Shipley": {
      "value": 68,
      "overallRank": 357,
      "positionRank": 100,
      "position": "RB",
      "team": "PHI",
      "trend30Day": 10,
      "sleeperId": "11577"
    },
    "Kendrick Bourne": {
      "value": 64,
      "overallRank": 358,
      "positionRank": 137,
      "position": "WR",
      "team": "ARI",
      "trend30Day": -38,
      "sleeperId": "4454"
    },
    "Devin Singletary": {
      "value": 62,
      "overallRank": 359,
      "positionRank": 101,
      "position": "RB",
      "team": "NYG",
      "trend30Day": -95,
      "sleeperId": "6130"
    },
    "Malik Davis": {
      "value": 61,
      "overallRank": 360,
      "positionRank": 102,
      "position": "RB",
      "team": "DAL",
      "trend30Day": 61,
      "sleeperId": "8800"
    },
    "KaVontae Turpin": {
      "value": 59,
      "overallRank": 361,
      "positionRank": 138,
      "position": "WR",
      "team": "DAL",
      "trend30Day": -1,
      "sleeperId": "8917"
    },
    "Jimmy Horn": {
      "value": 56,
      "overallRank": 362,
      "positionRank": 139,
      "position": "WR",
      "team": "CAR",
      "trend30Day": -70,
      "sleeperId": "12523"
    },
    "Ty Johnson": {
      "value": 55,
      "overallRank": 363,
      "positionRank": 103,
      "position": "RB",
      "team": "BUF",
      "trend30Day": 55,
      "sleeperId": "6039"
    },
    "Tutu Atwell": {
      "value": 55,
      "overallRank": 364,
      "positionRank": 140,
      "position": "WR",
      "team": "MIA",
      "trend30Day": -41,
      "sleeperId": "7562"
    },
    "Jarrett Stidham": {
      "value": 53,
      "overallRank": 365,
      "positionRank": 66,
      "position": "QB",
      "team": "DEN",
      "trend30Day": 53,
      "sleeperId": "6136"
    },
    "Efton Chism": {
      "value": 47,
      "overallRank": 366,
      "positionRank": 141,
      "position": "WR",
      "team": "NE",
      "trend30Day": -31,
      "sleeperId": "12542"
    },
    "Tai Felton": {
      "value": 46,
      "overallRank": 367,
      "positionRank": 142,
      "position": "WR",
      "team": "MIN",
      "trend30Day": -8,
      "sleeperId": "12496"
    },
    "Erick All": {
      "value": 44,
      "overallRank": 368,
      "positionRank": 57,
      "position": "TE",
      "team": "CIN",
      "trend30Day": 44,
      "sleeperId": "11592"
    },
    "Konata Mumpfield": {
      "value": 44,
      "overallRank": 369,
      "positionRank": 143,
      "position": "WR",
      "team": "LAR",
      "trend30Day": 44,
      "sleeperId": "12718"
    },
    "Xavier Restrepo": {
      "value": 40,
      "overallRank": 370,
      "positionRank": 144,
      "position": "WR",
      "team": "TEN",
      "trend30Day": 40,
      "sleeperId": "12520"
    },
    "Daniel Bellinger": {
      "value": 31,
      "overallRank": 371,
      "positionRank": 58,
      "position": "TE",
      "team": "TEN",
      "trend30Day": 11,
      "sleeperId": "8225"
    },
    "Arian Smith": {
      "value": 31,
      "overallRank": 372,
      "positionRank": 145,
      "position": "WR",
      "team": "NYJ",
      "trend30Day": 31,
      "sleeperId": "12539"
    },
    "Chris Brooks": {
      "value": 29,
      "overallRank": 373,
      "positionRank": 104,
      "position": "RB",
      "team": "GB",
      "trend30Day": 29,
      "sleeperId": "11370"
    },
    "Joshua Palmer": {
      "value": 24,
      "overallRank": 374,
      "positionRank": 146,
      "position": "WR",
      "team": "BUF",
      "trend30Day": -56,
      "sleeperId": "7670"
    },
    "Devontez Walker": {
      "value": 23,
      "overallRank": 375,
      "positionRank": 147,
      "position": "WR",
      "team": "BAL",
      "trend30Day": -2,
      "sleeperId": "11629"
    },
    "Tyler Huntley": {
      "value": 19,
      "overallRank": 376,
      "positionRank": 67,
      "position": "QB",
      "team": "BAL",
      "trend30Day": -45,
      "sleeperId": "7083"
    },
    "Samaje Perine": {
      "value": 17,
      "overallRank": 377,
      "positionRank": 105,
      "position": "RB",
      "team": "CIN",
      "trend30Day": 10,
      "sleeperId": "4147"
    },
    "Raheim Sanders": {
      "value": 16,
      "overallRank": 378,
      "positionRank": 106,
      "position": "RB",
      "team": "CLE",
      "trend30Day": 16,
      "sleeperId": "12472"
    },
    "Cade Stover": {
      "value": 13,
      "overallRank": 379,
      "positionRank": 59,
      "position": "TE",
      "team": "HOU",
      "trend30Day": -8,
      "sleeperId": "11599"
    },
    "Elijah Higgins": {
      "value": 10,
      "overallRank": 380,
      "positionRank": 60,
      "position": "TE",
      "team": "ARI",
      "trend30Day": 10,
      "sleeperId": "10231"
    },
    "Damien Martinez": {
      "value": 9,
      "overallRank": 381,
      "positionRank": 107,
      "position": "RB",
      "team": "GB",
      "trend30Day": 9,
      "sleeperId": "12462"
    },
    "Tahj Washington": {
      "value": 1,
      "overallRank": 382,
      "positionRank": 148,
      "position": "WR",
      "team": "MIA",
      "trend30Day": 1,
      "sleeperId": "11821"
    }
  }
}